{"id": 118, "session": 29, "time": 147157.0, "compound": "dry_compound", "date": "2025-04-23 00:00:00", "temperature": 28.89559555053711, "comments": "", "fuel": 35, "tyrePressure": {"frontRight": 27.151504516601562, "frontLeft": 27.13743019104004, "rearRight": 26.76071548461914, "rearLeft": 26.915523529052734}, "tyreTemperatures": {"frontRight": 87, "frontLeft": 84, "rearRight": 89, "rearLeft": 89}, "usure_plaquette": 28.79198169708252, "lap_type": "Chrono", "lap_index_session": 5, "lap_index_tyre": 2, "sectors": {"sector1": 43392, "sector2": 64928, "sector3": 38837}, "tc_level": 6, "abs_level": 6, "valid": true, "tyre_set": 2, "driver": "Camille", "car": "McLaren 720S GT3", "track": "SPA", "csv_file": "C:\\Users\\camil\\Documents\\Sport auto\\data_analysis\\backend\\telemetry_data\\lap_5_20250423091348.csv"}